jupyterlab_heroku/__init__.py
jupyterlab_heroku/_version.py
jupyterlab_heroku/handlers.py
jupyterlab_heroku/heroku.py
jupyterlab_heroku-0.2.1.dist-info/LICENSE
jupyterlab_heroku-0.2.1.dist-info/METADATA
jupyterlab_heroku-0.2.1.dist-info/WHEEL
jupyterlab_heroku-0.2.1.dist-info/top_level.txt
jupyterlab_heroku-0.2.1.dist-info/RECORD
