Metadata-Version: 2.1
Name: jupyterlab-heroku
Version: 0.2.1
Summary: A server extension for the JupyterLab Heroku extension
Home-page: UNKNOWN
Author: Jeremy Tuloup
License: UNKNOWN
Platform: UNKNOWN
Requires-Dist: jupyterlab
